odoo/addons/product_tag_pricelist/README.rst
odoo/addons/product_tag_pricelist/__init__.py
odoo/addons/product_tag_pricelist/__manifest__.py
odoo/addons/product_tag_pricelist/i18n/es.po
odoo/addons/product_tag_pricelist/models/__init__.py
odoo/addons/product_tag_pricelist/models/product_pricelist.py
odoo/addons/product_tag_pricelist/models/product_pricelist_item.py
odoo/addons/product_tag_pricelist/models/product_product.py
odoo/addons/product_tag_pricelist/models/product_template.py
odoo/addons/product_tag_pricelist/readme/CONFIGURE.md
odoo/addons/product_tag_pricelist/readme/CONTRIBUTORS.md
odoo/addons/product_tag_pricelist/readme/DESCRIPTION.md
odoo/addons/product_tag_pricelist/readme/ROADMAP.md
odoo/addons/product_tag_pricelist/readme/USAGE.md
odoo/addons/product_tag_pricelist/static/description/icon.png
odoo/addons/product_tag_pricelist/static/description/index.html
odoo/addons/product_tag_pricelist/tests/__init__.py
odoo/addons/product_tag_pricelist/tests/test_product_tag_pricelist.py
odoo/addons/product_tag_pricelist/views/product_pricelist_views.xml
odoo_addon_product_tag_pricelist-17.0.2.0.0.dist-info/METADATA
odoo_addon_product_tag_pricelist-17.0.2.0.0.dist-info/WHEEL
odoo_addon_product_tag_pricelist-17.0.2.0.0.dist-info/top_level.txt
odoo_addon_product_tag_pricelist-17.0.2.0.0.dist-info/RECORD
